forkyanimdl/__init__.py
forkyanimdl/__main__.py
forkyanimdl/core/__init__.py
forkyanimdl/core/__version__.py
forkyanimdl/core/cli/__init__.py
forkyanimdl/core/cli/commands/__init__.py
forkyanimdl/core/cli/commands/download.py
forkyanimdl/core/cli/commands/grab.py
forkyanimdl/core/cli/commands/schedule.py
forkyanimdl/core/cli/commands/search.py
forkyanimdl/core/cli/commands/stream.py
forkyanimdl/core/cli/commands/update.py
forkyanimdl/core/cli/exit_codes.py
forkyanimdl/core/cli/helpers/__init__.py
forkyanimdl/core/cli/helpers/aniskip.py
forkyanimdl/core/cli/helpers/banner.py
forkyanimdl/core/cli/helpers/constants.py
forkyanimdl/core/cli/helpers/decorators.py
forkyanimdl/core/cli/helpers/fuzzysearch.py
forkyanimdl/core/cli/helpers/intelliq.py
forkyanimdl/core/cli/helpers/logger.py
forkyanimdl/core/cli/helpers/player.py
forkyanimdl/core/cli/helpers/players/__init__.py
forkyanimdl/core/cli/helpers/players/android.py
forkyanimdl/core/cli/helpers/players/base_player.py
forkyanimdl/core/cli/helpers/players/ffplay.py
forkyanimdl/core/cli/helpers/players/mpv.py
forkyanimdl/core/cli/helpers/players/vlc.py
forkyanimdl/core/cli/helpers/processors.py
forkyanimdl/core/cli/helpers/prompts.py
forkyanimdl/core/cli/helpers/rpc.py
forkyanimdl/core/cli/helpers/searcher.py
forkyanimdl/core/cli/helpers/special.py
forkyanimdl/core/cli/helpers/stream_handlers.py
forkyanimdl/core/cli/http_client.py
forkyanimdl/core/codebase/__init__.py
forkyanimdl/core/codebase/downloader/__init__.py
forkyanimdl/core/codebase/downloader/ffmpeg.py
forkyanimdl/core/codebase/downloader/handle.py
forkyanimdl/core/codebase/downloader/hls.py
forkyanimdl/core/codebase/downloader/idmanlib.py
forkyanimdl/core/codebase/extractors/__init__.py
forkyanimdl/core/codebase/extractors/dailymotion/__init__.py
forkyanimdl/core/codebase/extractors/doodstream/__init__.py
forkyanimdl/core/codebase/extractors/gogoplay/__init__.py
forkyanimdl/core/codebase/extractors/mp4upload/__init__.py
forkyanimdl-1.7.27.dist-info/entry_points.txt
forkyanimdl-1.7.27.dist-info/LICENSE
forkyanimdl-1.7.27.dist-info/METADATA
forkyanimdl-1.7.27.dist-info/WHEEL
forkyanimdl-1.7.27.dist-info/RECORD
